{
  "trackers": [
    {
      "type": "unknown",
      "url": "https://infolettres.duministeredelaculture.fr/preferences/assets/css/mbExtension.min.css"
    },
    {
      "type": "unknown",
      "url": "https://tarteaucitron.io/load.js?domain=nuitdesmusees.culture.gouv.fr&uuid=cb6c31eaf0d65c6f8768c5734dd1a8df6bfd7780"
    },
    {
      "type": "instagram",
      "url": "https://www.instagram.com/embed.js",
      "details": {
        "id": "instagram",
        "message": "Dont embed instagram scripts, use your own embed"
      }
    },
    {
      "type": "instagram",
      "url": "https://www.instagram.com/p/DIds7TMosBs/embed/?cr=1&v=14&wp=326&rd=https%3A%2F%2Fnuitdesmusees.culture.gouv.fr&rp=%2F#%7B%22ci%22%3A0%2C%22os%22%3A2213.699999999997%2C%22ls%22%3A1221.6000000000058%2C%22le%22%3A1408.6000000000058%7D",
      "details": {
        "id": "instagram",
        "message": "Dont embed instagram scripts, use your own embed"
      }
    },
    {
      "type": "instagram",
      "url": "https://www.instagram.com/reel/DGnuQEVik-2/embed/?cr=1&v=14&wp=326&rd=https%3A%2F%2Fnuitdesmusees.culture.gouv.fr&rp=%2F#%7B%22ci%22%3A1%2C%22os%22%3A2216.100000000006%2C%22ls%22%3A1221.6000000000058%2C%22le%22%3A1408.6000000000058%7D",
      "details": {
        "id": "instagram",
        "message": "Dont embed instagram scripts, use your own embed"
      }
    },
    {
      "type": "instagram",
      "url": "https://www.instagram.com/reel/DGgKtvCN0GH/embed/?cr=1&v=14&wp=326&rd=https%3A%2F%2Fnuitdesmusees.culture.gouv.fr&rp=%2F#%7B%22ci%22%3A2%2C%22os%22%3A2217.600000000006%2C%22ls%22%3A1221.6000000000058%2C%22le%22%3A1408.6000000000058%7D",
      "details": {
        "id": "instagram",
        "message": "Dont embed instagram scripts, use your own embed"
      }
    },
    {
      "type": "instagram",
      "url": "https://static.cdninstagram.com/rsrc.php/v5/yM/l/0,cross/ap3Iw73DoWw.css",
      "details": {
        "id": "instagram",
        "message": "Dont embed instagram scripts, use your own embed"
      }
    },
    {
      "type": "instagram",
      "url": "https://static.cdninstagram.com/rsrc.php/v5/y8/l/0,cross/QnN1jmRta9t.css",
      "details": {
        "id": "instagram",
        "message": "Dont embed instagram scripts, use your own embed"
      }
    },
    {
      "type": "instagram",
      "url": "https://static.cdninstagram.com/rsrc.php/v5/yN/l/0,cross/GLwiNGdsX9O.css",
      "details": {
        "id": "instagram",
        "message": "Dont embed instagram scripts, use your own embed"
      }
    },
    {
      "type": "instagram",
      "url": "https://static.cdninstagram.com/rsrc.php/v5/yK/l/0,cross/BE5S-QoKwTV.css",
      "details": {
        "id": "instagram",
        "message": "Dont embed instagram scripts, use your own embed"
      }
    },
    {
      "type": "instagram",
      "url": "https://static.cdninstagram.com/rsrc.php/v5/yk/l/0,cross/Iu8c4oMa__n.css",
      "details": {
        "id": "instagram",
        "message": "Dont embed instagram scripts, use your own embed"
      }
    },
    {
      "type": "instagram",
      "url": "https://scontent-lhr6-2.cdninstagram.com/v/t51.2885-19/475022361_613200377964180_449344027979742467_n.jpg?stp=dst-jpg_s150x150_tt6&_nc_ht=scontent-lhr6-2.cdninstagram.com&_nc_cat=100&_nc_oc=Q6cZ2QFYtQmnJCsi3DKtjp6qe9RwctAWAMcGnMPkGgobGwTo_oER6HoAkUy9ts-7TB-b7cY&_nc_ohc=zpWx2G21sN8Q7kNvwFpZ1hn&_nc_gid=dlAwftw-0BsopJ-grV3xOQ&edm=APs17CUBAAAA&ccb=7-5&oh=00_AfTWFFz-SNjINFN8K08OwLaiGbwcDcZFE72XVDLYxJ5Hjw&oe=686F8D9D&_nc_sid=10d13b",
      "details": {
        "id": "instagram",
        "message": "Dont embed instagram scripts, use your own embed"
      }
    },
    {
      "type": "instagram",
      "url": "https://scontent-lhr6-2.cdninstagram.com/v/t51.2885-19/491417437_18403605190096145_6216946447330413935_n.jpg?stp=dst-jpg_s150x150_tt6&_nc_ht=scontent-lhr6-2.cdninstagram.com&_nc_cat=105&_nc_oc=Q6cZ2QFYtQmnJCsi3DKtjp6qe9RwctAWAMcGnMPkGgobGwTo_oER6HoAkUy9ts-7TB-b7cY&_nc_ohc=T_I2eC2wS8IQ7kNvwHWH3ZT&_nc_gid=dlAwftw-0BsopJ-grV3xOQ&edm=APs17CUBAAAA&ccb=7-5&oh=00_AfTt6MH9MlpMG3cn-Wjqs0pGeJ4r2B_i6fbdFimMnYUQEw&oe=686FA5CF&_nc_sid=10d13b",
      "details": {
        "id": "instagram",
        "message": "Dont embed instagram scripts, use your own embed"
      }
    },
    {
      "type": "instagram",
      "url": "https://static.cdninstagram.com/rsrc.php/v4/y-/r/N11r1oTncio.js",
      "details": {
        "id": "instagram",
        "message": "Dont embed instagram scripts, use your own embed"
      }
    },
    {
      "type": "instagram",
      "url": "https://static.cdninstagram.com/rsrc.php/v5/yM/l/0,cross/ap3Iw73DoWw.css",
      "details": {
        "id": "instagram",
        "message": "Dont embed instagram scripts, use your own embed"
      }
    },
    {
      "type": "instagram",
      "url": "https://static.cdninstagram.com/rsrc.php/v5/yN/l/0,cross/GLwiNGdsX9O.css",
      "details": {
        "id": "instagram",
        "message": "Dont embed instagram scripts, use your own embed"
      }
    },
    {
      "type": "instagram",
      "url": "https://static.cdninstagram.com/rsrc.php/v5/yk/l/0,cross/Iu8c4oMa__n.css",
      "details": {
        "id": "instagram",
        "message": "Dont embed instagram scripts, use your own embed"
      }
    },
    {
      "type": "instagram",
      "url": "https://scontent-lhr6-2.cdninstagram.com/v/t51.2885-19/491417437_18403605190096145_6216946447330413935_n.jpg?stp=dst-jpg_s150x150_tt6&_nc_ht=scontent-lhr6-2.cdninstagram.com&_nc_cat=105&_nc_oc=Q6cZ2QGKEIoGTWz5TmxWA56o3OFRD2Geb-qWD9p3QeX1Uo9fSCECK9Fo60Ua9W4YmYqCOdw&_nc_ohc=T_I2eC2wS8IQ7kNvwHWH3ZT&_nc_gid=VBXboijIkqBvjkkQVU_b5g&edm=APs17CUBAAAA&ccb=7-5&oh=00_AfS2trtJCIVXPI2Rdo5L-zYGqBeh3fVB4IvWV_KHA_lWcQ&oe=686FA5CF&_nc_sid=10d13b",
      "details": {
        "id": "instagram",
        "message": "Dont embed instagram scripts, use your own embed"
      }
    },
    {
      "type": "instagram",
      "url": "https://scontent-lhr8-2.cdninstagram.com/v/t51.2885-19/489893797_4064397110458962_2884751982814902282_n.jpg?stp=dst-jpg_s150x150_tt6&_nc_ht=scontent-lhr8-2.cdninstagram.com&_nc_cat=106&_nc_oc=Q6cZ2QGKEIoGTWz5TmxWA56o3OFRD2Geb-qWD9p3QeX1Uo9fSCECK9Fo60Ua9W4YmYqCOdw&_nc_ohc=Thfgv8Ak-tgQ7kNvwGieW1G&_nc_gid=VBXboijIkqBvjkkQVU_b5g&edm=APs17CUBAAAA&ccb=7-5&oh=00_AfQS28BqxJpgTig1Jckppjo2ZuLCvvc5bvOPWBv9pMoNlQ&oe=686F9382&_nc_sid=10d13b",
      "details": {
        "id": "instagram",
        "message": "Dont embed instagram scripts, use your own embed"
      }
    },
    {
      "type": "instagram",
      "url": "https://static.cdninstagram.com/rsrc.php/v4/y-/r/N11r1oTncio.js",
      "details": {
        "id": "instagram",
        "message": "Dont embed instagram scripts, use your own embed"
      }
    },
    {
      "type": "instagram",
      "url": "https://static.cdninstagram.com/rsrc.php/v5/yM/l/0,cross/ap3Iw73DoWw.css",
      "details": {
        "id": "instagram",
        "message": "Dont embed instagram scripts, use your own embed"
      }
    },
    {
      "type": "instagram",
      "url": "https://static.cdninstagram.com/rsrc.php/v5/y8/l/0,cross/QnN1jmRta9t.css",
      "details": {
        "id": "instagram",
        "message": "Dont embed instagram scripts, use your own embed"
      }
    },
    {
      "type": "instagram",
      "url": "https://static.cdninstagram.com/rsrc.php/v5/yN/l/0,cross/GLwiNGdsX9O.css",
      "details": {
        "id": "instagram",
        "message": "Dont embed instagram scripts, use your own embed"
      }
    },
    {
      "type": "instagram",
      "url": "https://static.cdninstagram.com/rsrc.php/v5/yk/l/0,cross/Iu8c4oMa__n.css",
      "details": {
        "id": "instagram",
        "message": "Dont embed instagram scripts, use your own embed"
      }
    },
    {
      "type": "instagram",
      "url": "https://scontent-lhr6-2.cdninstagram.com/v/t51.2885-19/491417437_18403605190096145_6216946447330413935_n.jpg?stp=dst-jpg_s150x150_tt6&_nc_ht=scontent-lhr6-2.cdninstagram.com&_nc_cat=105&_nc_oc=Q6cZ2QHkAKD4froFrpUgjZqOx0OVY6coZHRdNImYrX2t-ricrxjfSqIVifI0RgyLfGzHI_c&_nc_ohc=T_I2eC2wS8IQ7kNvwHWH3ZT&_nc_gid=ZXIaHt-I0_03PJaIlVEQDw&edm=APs17CUBAAAA&ccb=7-5&oh=00_AfRiRVp8CXzRtVZ1UZ8Hd6ogvFTYjqKDXH8TdugM_iFgFw&oe=686FA5CF&_nc_sid=10d13b",
      "details": {
        "id": "instagram",
        "message": "Dont embed instagram scripts, use your own embed"
      }
    },
    {
      "type": "instagram",
      "url": "https://scontent-lhr6-2.cdninstagram.com/v/t51.2885-19/475022361_613200377964180_449344027979742467_n.jpg?stp=dst-jpg_s150x150_tt6&_nc_ht=scontent-lhr6-2.cdninstagram.com&_nc_cat=100&_nc_oc=Q6cZ2QHkAKD4froFrpUgjZqOx0OVY6coZHRdNImYrX2t-ricrxjfSqIVifI0RgyLfGzHI_c&_nc_ohc=zpWx2G21sN8Q7kNvwFpZ1hn&_nc_gid=ZXIaHt-I0_03PJaIlVEQDw&edm=APs17CUBAAAA&ccb=7-5&oh=00_AfRhpMkLjstm09DA3W7ochiu6kcJsCXt5B_HYrstrHi4fA&oe=686F8D9D&_nc_sid=10d13b",
      "details": {
        "id": "instagram",
        "message": "Dont embed instagram scripts, use your own embed"
      }
    },
    {
      "type": "instagram",
      "url": "https://static.cdninstagram.com/rsrc.php/v4/y-/r/N11r1oTncio.js",
      "details": {
        "id": "instagram",
        "message": "Dont embed instagram scripts, use your own embed"
      }
    },
    {
      "type": "instagram",
      "url": "https://scontent-lhr6-2.cdninstagram.com/v/t51.2885-15/491416155_18499954714062556_3540713235031999312_n.jpg?stp=dst-jpg_e35_p640x640_sh0.08_tt6&efg=eyJ2ZW5jb2RlX3RhZyI6ImltYWdlX3VybGdlbi4xMDgweDEzNTAuc2RyLmY3NTc2MS5kZWZhdWx0X2ltYWdlIn0&_nc_ht=scontent-lhr6-2.cdninstagram.com&_nc_cat=104&_nc_oc=Q6cZ2QHkAKD4froFrpUgjZqOx0OVY6coZHRdNImYrX2t-ricrxjfSqIVifI0RgyLfGzHI_c&_nc_ohc=P9WTy417ThMQ7kNvwGMx2c3&_nc_gid=ZXIaHt-I0_03PJaIlVEQDw&edm=APs17CUBAAAA&ccb=7-5&oh=00_AfRCoXKWHk0RaCdUB9aRIo_D8PkljV7UrVUaIo2xDfmUSg&oe=686F9270&_nc_sid=10d13b",
      "details": {
        "id": "instagram",
        "message": "Dont embed instagram scripts, use your own embed"
      }
    },
    {
      "type": "instagram",
      "url": "https://scontent-lhr6-2.cdninstagram.com/v/t51.2885-15/499958911_18407036665096145_5533809070862960173_n.jpg?stp=c0.180.1440.1440a_dst-jpg_e35_s150x150_tt6&efg=eyJ2ZW5jb2RlX3RhZyI6ImltYWdlX3VybGdlbi4xNDQweDE4MDAuc2RyLmY3NTc2MS5kZWZhdWx0X2ltYWdlIn0&_nc_ht=scontent-lhr6-2.cdninstagram.com&_nc_cat=105&_nc_oc=Q6cZ2QHkAKD4froFrpUgjZqOx0OVY6coZHRdNImYrX2t-ricrxjfSqIVifI0RgyLfGzHI_c&_nc_ohc=vXUWMw6iZIYQ7kNvwGOWBYb&_nc_gid=ZXIaHt-I0_03PJaIlVEQDw&edm=APs17CUBAAAA&ccb=7-5&oh=00_AfSglPViThjLf-cU7EQGDio0NTJmcD2pK1ORjAyRpZZDmg&oe=686F91DA&_nc_sid=10d13b",
      "details": {
        "id": "instagram",
        "message": "Dont embed instagram scripts, use your own embed"
      }
    },
    {
      "type": "instagram",
      "url": "https://scontent-lhr6-2.cdninstagram.com/v/t51.2885-15/502397979_595318813590880_7246879671994882775_n.jpg?stp=c0.420.1080.1080a_dst-jpg_e15_s150x150_tt6&efg=eyJ2ZW5jb2RlX3RhZyI6ImltYWdlX3VybGdlbi4xMDgweDE5MjAuc2RyLmY3MTg3OC5kZWZhdWx0X2NvdmVyX2ZyYW1lIn0&_nc_ht=scontent-lhr6-2.cdninstagram.com&_nc_cat=104&_nc_oc=Q6cZ2QHkAKD4froFrpUgjZqOx0OVY6coZHRdNImYrX2t-ricrxjfSqIVifI0RgyLfGzHI_c&_nc_ohc=UOYc_9S6ddUQ7kNvwGDNLCw&_nc_gid=ZXIaHt-I0_03PJaIlVEQDw&edm=APs17CUBAAAA&ccb=7-5&oh=00_AfSbachsS0BaONS4P4Zd-AIBhaE-_RQyqKq74ZU_8Lt1TA&oe=686F9BCF&_nc_sid=10d13b",
      "details": {
        "id": "instagram",
        "message": "Dont embed instagram scripts, use your own embed"
      }
    },
    {
      "type": "instagram",
      "url": "https://scontent-lhr6-2.cdninstagram.com/v/t51.2885-15/483920772_18396597193096145_5734296250571458704_n.jpg?stp=dst-jpg_e15_p640x640_tt6&efg=eyJ2ZW5jb2RlX3RhZyI6ImltYWdlX3VybGdlbi43MjB4MTI4MC5zZHIuZjc1NzYxLmRlZmF1bHRfY292ZXJfZnJhbWUifQ&_nc_ht=scontent-lhr6-2.cdninstagram.com&_nc_cat=105&_nc_oc=Q6cZ2QFYtQmnJCsi3DKtjp6qe9RwctAWAMcGnMPkGgobGwTo_oER6HoAkUy9ts-7TB-b7cY&_nc_ohc=8O0OJIIYfRwQ7kNvwFB_Ekn&_nc_gid=dlAwftw-0BsopJ-grV3xOQ&edm=APs17CUBAAAA&ccb=7-5&oh=00_AfS1np7Hx7sPoLiDGX-_fm65uXLvMugbZIrdhzwUm5IL0A&oe=686F98DE&_nc_sid=10d13b",
      "details": {
        "id": "instagram",
        "message": "Dont embed instagram scripts, use your own embed"
      }
    },
    {
      "type": "instagram",
      "url": "https://scontent-lhr8-1.cdninstagram.com/v/t51.2885-15/472631739_18487771645038944_6126232810882532026_n.jpg?stp=dst-jpg_e35_p640x640_sh0.08_tt6&efg=eyJ2ZW5jb2RlX3RhZyI6ImltYWdlX3VybGdlbi4zMjE2eDU3MTIuc2RyLmY3NTc2MS5kZWZhdWx0X2NvdmVyX2ZyYW1lIn0&_nc_ht=scontent-lhr8-1.cdninstagram.com&_nc_cat=108&_nc_oc=Q6cZ2QGKEIoGTWz5TmxWA56o3OFRD2Geb-qWD9p3QeX1Uo9fSCECK9Fo60Ua9W4YmYqCOdw&_nc_ohc=QNrBy8XCvPAQ7kNvwFsM11f&_nc_gid=VBXboijIkqBvjkkQVU_b5g&edm=APs17CUBAAAA&ccb=7-5&oh=00_AfT6V4va9b-Junn0V3xX2Qygi0JLD7QLQmZjf_hQXugjmw&oe=686F8E92&_nc_sid=10d13b",
      "details": {
        "id": "instagram",
        "message": "Dont embed instagram scripts, use your own embed"
      }
    },
    {
      "type": "instagram",
      "url": "https://scontent-lhr6-2.cdninstagram.com/v/t51.2885-15/515820049_18413178307096145_1194770953003528856_n.jpg?stp=c0.135.1080.1080a_dst-jpg_e35_s150x150_tt6&efg=eyJ2ZW5jb2RlX3RhZyI6ImltYWdlX3VybGdlbi4xMDgweDEzNTAuc2RyLmY4Mjc4Ny5kZWZhdWx0X2ltYWdlIn0&_nc_ht=scontent-lhr6-2.cdninstagram.com&_nc_cat=105&_nc_oc=Q6cZ2QFYtQmnJCsi3DKtjp6qe9RwctAWAMcGnMPkGgobGwTo_oER6HoAkUy9ts-7TB-b7cY&_nc_ohc=2N_TcdWbCK4Q7kNvwETOG2i&_nc_gid=dlAwftw-0BsopJ-grV3xOQ&edm=APs17CUBAAAA&ccb=7-5&oh=00_AfQbhtokoNghwDSVur3ext2fMmWCe3I4fgZ5oIRCTwggww&oe=686F94B9&_nc_sid=10d13b",
      "details": {
        "id": "instagram",
        "message": "Dont embed instagram scripts, use your own embed"
      }
    },
    {
      "type": "instagram",
      "url": "https://scontent-lhr6-2.cdninstagram.com/v/t51.2885-15/514407115_18412785673096145_3563152131192149019_n.jpg?stp=c0.135.1080.1080a_dst-jpg_e35_s150x150_tt6&efg=eyJ2ZW5jb2RlX3RhZyI6ImltYWdlX3VybGdlbi4xMDgweDEzNTAuc2RyLmY4Mjc4Ny5kZWZhdWx0X2ltYWdlIn0&_nc_ht=scontent-lhr6-2.cdninstagram.com&_nc_cat=105&_nc_oc=Q6cZ2QFYtQmnJCsi3DKtjp6qe9RwctAWAMcGnMPkGgobGwTo_oER6HoAkUy9ts-7TB-b7cY&_nc_ohc=AtyAwQdDaF4Q7kNvwH9dg7r&_nc_gid=dlAwftw-0BsopJ-grV3xOQ&edm=APs17CUBAAAA&ccb=7-5&oh=00_AfT1TxH7E4nMI48iXfZvB7kCIHNlPqsG0phkkV4tg4fYfg&oe=686F9B03&_nc_sid=10d13b",
      "details": {
        "id": "instagram",
        "message": "Dont embed instagram scripts, use your own embed"
      }
    },
    {
      "type": "instagram",
      "url": "https://scontent-lhr6-1.cdninstagram.com/v/t51.2885-15/503379708_1249945670013470_4806345216578601115_n.jpg?stp=c0.280.720.720a_dst-jpg_e15_s150x150_tt6&efg=eyJ2ZW5jb2RlX3RhZyI6ImltYWdlX3VybGdlbi43MjB4MTI4MC5zZHIuZjcxODc4LmRlZmF1bHRfY292ZXJfZnJhbWUifQ&_nc_ht=scontent-lhr6-1.cdninstagram.com&_nc_cat=102&_nc_oc=Q6cZ2QGKEIoGTWz5TmxWA56o3OFRD2Geb-qWD9p3QeX1Uo9fSCECK9Fo60Ua9W4YmYqCOdw&_nc_ohc=unOCyHn80oUQ7kNvwHxyXlT&_nc_gid=VBXboijIkqBvjkkQVU_b5g&edm=APs17CUBAAAA&ccb=7-5&oh=00_AfSe8u2GtPnTTkDnXmYimkLNNEPBwe0DHhAGO6IoPhm01g&oe=686FBC14&_nc_sid=10d13b",
      "details": {
        "id": "instagram",
        "message": "Dont embed instagram scripts, use your own embed"
      }
    },
    {
      "type": "instagram",
      "url": "https://scontent-lhr6-2.cdninstagram.com/v/t51.29350-15/460196228_564195029271616_8900335966409290528_n.jpg?stp=c0.180.1440.1440a_dst-jpg_e35_s150x150_tt6&efg=eyJ2ZW5jb2RlX3RhZyI6ImltYWdlX3VybGdlbi4xNDQweDE4MDAuc2RyLmYyOTM1MC5kZWZhdWx0X2ltYWdlIn0&_nc_ht=scontent-lhr6-2.cdninstagram.com&_nc_cat=104&_nc_oc=Q6cZ2QGKEIoGTWz5TmxWA56o3OFRD2Geb-qWD9p3QeX1Uo9fSCECK9Fo60Ua9W4YmYqCOdw&_nc_ohc=VDhuQHw2ADMQ7kNvwG7qB4Z&_nc_gid=VBXboijIkqBvjkkQVU_b5g&edm=APs17CUBAAAA&ccb=7-5&oh=00_AfQQrQ9L6aeaJ0pKyUVGKqyKOo0vnG5RHk2lQ0uDlqoM9g&oe=686F8AC0&_nc_sid=10d13b",
      "details": {
        "id": "instagram",
        "message": "Dont embed instagram scripts, use your own embed"
      }
    },
    {
      "type": "instagram",
      "url": "https://static.cdninstagram.com/rsrc.php/v4/y_/r/Kq06toTJMFl.png",
      "details": {
        "id": "instagram",
        "message": "Dont embed instagram scripts, use your own embed"
      }
    },
    {
      "type": "instagram",
      "url": "https://static.cdninstagram.com/rsrc.php/v4/y_/r/Kq06toTJMFl.png",
      "details": {
        "id": "instagram",
        "message": "Dont embed instagram scripts, use your own embed"
      }
    },
    {
      "type": "instagram",
      "url": "https://static.cdninstagram.com/rsrc.php/v4/y_/r/Kq06toTJMFl.png",
      "details": {
        "id": "instagram",
        "message": "Dont embed instagram scripts, use your own embed"
      }
    },
    {
      "type": "instagram",
      "url": "https://static.cdninstagram.com/rsrc.php/v4ie0_4/yz/l/en_US/9A4jxq1W9F_.js",
      "details": {
        "id": "instagram",
        "message": "Dont embed instagram scripts, use your own embed"
      }
    },
    {
      "type": "instagram",
      "url": "https://static.cdninstagram.com/rsrc.php/v4ie0_4/yz/l/en_US/9A4jxq1W9F_.js",
      "details": {
        "id": "instagram",
        "message": "Dont embed instagram scripts, use your own embed"
      }
    },
    {
      "type": "instagram",
      "url": "https://static.cdninstagram.com/rsrc.php/v4/yo/r/049x90NZbnK.js",
      "details": {
        "id": "instagram",
        "message": "Dont embed instagram scripts, use your own embed"
      }
    },
    {
      "type": "instagram",
      "url": "https://static.cdninstagram.com/rsrc.php/v4/yW/r/xkrslkVsiqG.js",
      "details": {
        "id": "instagram",
        "message": "Dont embed instagram scripts, use your own embed"
      }
    },
    {
      "type": "instagram",
      "url": "https://static.cdninstagram.com/rsrc.php/v4i7M54/yq/l/en_US/7gDUunpN557.js",
      "details": {
        "id": "instagram",
        "message": "Dont embed instagram scripts, use your own embed"
      }
    },
    {
      "type": "instagram",
      "url": "https://static.cdninstagram.com/rsrc.php/v4/y3/r/J6CluukVXAD.js",
      "details": {
        "id": "instagram",
        "message": "Dont embed instagram scripts, use your own embed"
      }
    },
    {
      "type": "instagram",
      "url": "https://static.cdninstagram.com/rsrc.php/v4/y9/r/IAqkaiye5bw.js",
      "details": {
        "id": "instagram",
        "message": "Dont embed instagram scripts, use your own embed"
      }
    },
    {
      "type": "instagram",
      "url": "https://static.cdninstagram.com/rsrc.php/v4/yk/r/Ss1UIxBGCyJ.js",
      "details": {
        "id": "instagram",
        "message": "Dont embed instagram scripts, use your own embed"
      }
    },
    {
      "type": "instagram",
      "url": "https://static.cdninstagram.com/rsrc.php/v4/yy/r/PvmX1sWN9N3.js",
      "details": {
        "id": "instagram",
        "message": "Dont embed instagram scripts, use your own embed"
      }
    },
    {
      "type": "instagram",
      "url": "https://static.cdninstagram.com/rsrc.php/v4/y1/r/db_RQLQYjko.js",
      "details": {
        "id": "instagram",
        "message": "Dont embed instagram scripts, use your own embed"
      }
    },
    {
      "type": "instagram",
      "url": "https://static.cdninstagram.com/rsrc.php/v4/yo/r/049x90NZbnK.js",
      "details": {
        "id": "instagram",
        "message": "Dont embed instagram scripts, use your own embed"
      }
    },
    {
      "type": "instagram",
      "url": "https://static.cdninstagram.com/rsrc.php/v4/yW/r/xkrslkVsiqG.js",
      "details": {
        "id": "instagram",
        "message": "Dont embed instagram scripts, use your own embed"
      }
    },
    {
      "type": "instagram",
      "url": "https://static.cdninstagram.com/rsrc.php/v4i7M54/yq/l/en_US/7gDUunpN557.js",
      "details": {
        "id": "instagram",
        "message": "Dont embed instagram scripts, use your own embed"
      }
    },
    {
      "type": "instagram",
      "url": "https://static.cdninstagram.com/rsrc.php/v4/y3/r/J6CluukVXAD.js",
      "details": {
        "id": "instagram",
        "message": "Dont embed instagram scripts, use your own embed"
      }
    },
    {
      "type": "instagram",
      "url": "https://static.cdninstagram.com/rsrc.php/v4/y9/r/IAqkaiye5bw.js",
      "details": {
        "id": "instagram",
        "message": "Dont embed instagram scripts, use your own embed"
      }
    },
    {
      "type": "instagram",
      "url": "https://static.cdninstagram.com/rsrc.php/v4/yk/r/Ss1UIxBGCyJ.js",
      "details": {
        "id": "instagram",
        "message": "Dont embed instagram scripts, use your own embed"
      }
    },
    {
      "type": "instagram",
      "url": "https://static.cdninstagram.com/rsrc.php/v4/ya/r/g4bu-upR8Dy.js",
      "details": {
        "id": "instagram",
        "message": "Dont embed instagram scripts, use your own embed"
      }
    },
    {
      "type": "instagram",
      "url": "https://static.cdninstagram.com/rsrc.php/v4/yy/r/PvmX1sWN9N3.js",
      "details": {
        "id": "instagram",
        "message": "Dont embed instagram scripts, use your own embed"
      }
    },
    {
      "type": "instagram",
      "url": "https://static.cdninstagram.com/rsrc.php/v4ie0_4/yz/l/en_US/9A4jxq1W9F_.js",
      "details": {
        "id": "instagram",
        "message": "Dont embed instagram scripts, use your own embed"
      }
    },
    {
      "type": "instagram",
      "url": "https://static.cdninstagram.com/rsrc.php/v4/y5/r/n7PgHKffE0A.js",
      "details": {
        "id": "instagram",
        "message": "Dont embed instagram scripts, use your own embed"
      }
    },
    {
      "type": "instagram",
      "url": "https://static.cdninstagram.com/rsrc.php/v4/yt/r/sb4LIlsAARk.js",
      "details": {
        "id": "instagram",
        "message": "Dont embed instagram scripts, use your own embed"
      }
    },
    {
      "type": "instagram",
      "url": "https://static.cdninstagram.com/rsrc.php/v4/ye/r/5XTx2HWyFe4.js",
      "details": {
        "id": "instagram",
        "message": "Dont embed instagram scripts, use your own embed"
      }
    },
    {
      "type": "instagram",
      "url": "https://static.cdninstagram.com/rsrc.php/v4/y1/r/db_RQLQYjko.js",
      "details": {
        "id": "instagram",
        "message": "Dont embed instagram scripts, use your own embed"
      }
    },
    {
      "type": "instagram",
      "url": "https://static.cdninstagram.com/rsrc.php/v4/y5/r/n7PgHKffE0A.js",
      "details": {
        "id": "instagram",
        "message": "Dont embed instagram scripts, use your own embed"
      }
    },
    {
      "type": "instagram",
      "url": "https://static.cdninstagram.com/rsrc.php/v4/yt/r/sb4LIlsAARk.js",
      "details": {
        "id": "instagram",
        "message": "Dont embed instagram scripts, use your own embed"
      }
    },
    {
      "type": "instagram",
      "url": "https://static.cdninstagram.com/rsrc.php/v4/ye/r/5XTx2HWyFe4.js",
      "details": {
        "id": "instagram",
        "message": "Dont embed instagram scripts, use your own embed"
      }
    },
    {
      "type": "instagram",
      "url": "https://static.cdninstagram.com/rsrc.php/v4iI0n4/ye/l/en_US/llbKeTpY8ca.js",
      "details": {
        "id": "instagram",
        "message": "Dont embed instagram scripts, use your own embed"
      }
    },
    {
      "type": "instagram",
      "url": "https://static.cdninstagram.com/rsrc.php/v4/yF/r/JUQfRgDktxr.js",
      "details": {
        "id": "instagram",
        "message": "Dont embed instagram scripts, use your own embed"
      }
    },
    {
      "type": "instagram",
      "url": "https://static.cdninstagram.com/rsrc.php/v4ihVQ4/y4/l/en_US/tBdCjryrdB2.js",
      "details": {
        "id": "instagram",
        "message": "Dont embed instagram scripts, use your own embed"
      }
    },
    {
      "type": "instagram",
      "url": "https://static.cdninstagram.com/rsrc.php/v4/yo/r/049x90NZbnK.js",
      "details": {
        "id": "instagram",
        "message": "Dont embed instagram scripts, use your own embed"
      }
    },
    {
      "type": "instagram",
      "url": "https://static.cdninstagram.com/rsrc.php/v4/yW/r/xkrslkVsiqG.js",
      "details": {
        "id": "instagram",
        "message": "Dont embed instagram scripts, use your own embed"
      }
    },
    {
      "type": "instagram",
      "url": "https://static.cdninstagram.com/rsrc.php/v4i7M54/yq/l/en_US/7gDUunpN557.js",
      "details": {
        "id": "instagram",
        "message": "Dont embed instagram scripts, use your own embed"
      }
    },
    {
      "type": "instagram",
      "url": "https://static.cdninstagram.com/rsrc.php/v4/y3/r/J6CluukVXAD.js",
      "details": {
        "id": "instagram",
        "message": "Dont embed instagram scripts, use your own embed"
      }
    },
    {
      "type": "instagram",
      "url": "https://static.cdninstagram.com/rsrc.php/v4/y9/r/IAqkaiye5bw.js",
      "details": {
        "id": "instagram",
        "message": "Dont embed instagram scripts, use your own embed"
      }
    },
    {
      "type": "instagram",
      "url": "https://static.cdninstagram.com/rsrc.php/v4/yk/r/Ss1UIxBGCyJ.js",
      "details": {
        "id": "instagram",
        "message": "Dont embed instagram scripts, use your own embed"
      }
    },
    {
      "type": "instagram",
      "url": "https://static.cdninstagram.com/rsrc.php/v4/y7/r/R284lk3VJ6c.js",
      "details": {
        "id": "instagram",
        "message": "Dont embed instagram scripts, use your own embed"
      }
    },
    {
      "type": "instagram",
      "url": "https://static.cdninstagram.com/rsrc.php/v4/yO/r/FurF5tzLW7I.js",
      "details": {
        "id": "instagram",
        "message": "Dont embed instagram scripts, use your own embed"
      }
    },
    {
      "type": "instagram",
      "url": "https://static.cdninstagram.com/rsrc.php/v4/yF/r/EBVPsy6V8TR.js",
      "details": {
        "id": "instagram",
        "message": "Dont embed instagram scripts, use your own embed"
      }
    },
    {
      "type": "instagram",
      "url": "https://static.cdninstagram.com/rsrc.php/v4iI0n4/ye/l/en_US/llbKeTpY8ca.js",
      "details": {
        "id": "instagram",
        "message": "Dont embed instagram scripts, use your own embed"
      }
    },
    {
      "type": "instagram",
      "url": "https://static.cdninstagram.com/rsrc.php/v4/yi/r/03YxQA42w6B.js",
      "details": {
        "id": "instagram",
        "message": "Dont embed instagram scripts, use your own embed"
      }
    },
    {
      "type": "instagram",
      "url": "https://static.cdninstagram.com/rsrc.php/v4/yC/r/MS7A52kJp6_.js",
      "details": {
        "id": "instagram",
        "message": "Dont embed instagram scripts, use your own embed"
      }
    },
    {
      "type": "instagram",
      "url": "https://static.cdninstagram.com/rsrc.php/v4/y1/r/h9uo_iQ2ukL.js",
      "details": {
        "id": "instagram",
        "message": "Dont embed instagram scripts, use your own embed"
      }
    },
    {
      "type": "instagram",
      "url": "https://static.cdninstagram.com/rsrc.php/v4il5S4/ye/l/en_US/7PrnWnIJ8F0.js",
      "details": {
        "id": "instagram",
        "message": "Dont embed instagram scripts, use your own embed"
      }
    },
    {
      "type": "instagram",
      "url": "https://static.cdninstagram.com/rsrc.php/v4/yy/r/PvmX1sWN9N3.js",
      "details": {
        "id": "instagram",
        "message": "Dont embed instagram scripts, use your own embed"
      }
    },
    {
      "type": "instagram",
      "url": "https://static.cdninstagram.com/rsrc.php/v4/yF/r/JUQfRgDktxr.js",
      "details": {
        "id": "instagram",
        "message": "Dont embed instagram scripts, use your own embed"
      }
    },
    {
      "type": "instagram",
      "url": "https://static.cdninstagram.com/rsrc.php/v4ihVQ4/y4/l/en_US/tBdCjryrdB2.js",
      "details": {
        "id": "instagram",
        "message": "Dont embed instagram scripts, use your own embed"
      }
    },
    {
      "type": "instagram",
      "url": "https://static.cdninstagram.com/rsrc.php/v4/y7/r/R284lk3VJ6c.js",
      "details": {
        "id": "instagram",
        "message": "Dont embed instagram scripts, use your own embed"
      }
    },
    {
      "type": "instagram",
      "url": "https://static.cdninstagram.com/rsrc.php/v4/yO/r/FurF5tzLW7I.js",
      "details": {
        "id": "instagram",
        "message": "Dont embed instagram scripts, use your own embed"
      }
    },
    {
      "type": "instagram",
      "url": "https://static.cdninstagram.com/rsrc.php/v4/yF/r/EBVPsy6V8TR.js",
      "details": {
        "id": "instagram",
        "message": "Dont embed instagram scripts, use your own embed"
      }
    },
    {
      "type": "instagram",
      "url": "https://static.cdninstagram.com/rsrc.php/v4/yi/r/03YxQA42w6B.js",
      "details": {
        "id": "instagram",
        "message": "Dont embed instagram scripts, use your own embed"
      }
    },
    {
      "type": "instagram",
      "url": "https://static.cdninstagram.com/rsrc.php/v4/y7/r/R284lk3VJ6c.js",
      "details": {
        "id": "instagram",
        "message": "Dont embed instagram scripts, use your own embed"
      }
    },
    {
      "type": "instagram",
      "url": "https://static.cdninstagram.com/rsrc.php/v4/y1/r/db_RQLQYjko.js",
      "details": {
        "id": "instagram",
        "message": "Dont embed instagram scripts, use your own embed"
      }
    },
    {
      "type": "instagram",
      "url": "https://static.cdninstagram.com/rsrc.php/v4/y5/r/n7PgHKffE0A.js",
      "details": {
        "id": "instagram",
        "message": "Dont embed instagram scripts, use your own embed"
      }
    },
    {
      "type": "instagram",
      "url": "https://static.cdninstagram.com/rsrc.php/v4/yt/r/sb4LIlsAARk.js",
      "details": {
        "id": "instagram",
        "message": "Dont embed instagram scripts, use your own embed"
      }
    },
    {
      "type": "instagram",
      "url": "https://static.cdninstagram.com/rsrc.php/v4/yV/r/LIw0ZORBUrY.js",
      "details": {
        "id": "instagram",
        "message": "Dont embed instagram scripts, use your own embed"
      }
    },
    {
      "type": "instagram",
      "url": "https://static.cdninstagram.com/rsrc.php/v4iD-c4/ys/l/en_US/a7dyMktZWts.js",
      "details": {
        "id": "instagram",
        "message": "Dont embed instagram scripts, use your own embed"
      }
    },
    {
      "type": "instagram",
      "url": "https://static.cdninstagram.com/rsrc.php/v4/ye/r/5XTx2HWyFe4.js",
      "details": {
        "id": "instagram",
        "message": "Dont embed instagram scripts, use your own embed"
      }
    },
    {
      "type": "instagram",
      "url": "https://static.cdninstagram.com/rsrc.php/v4iI0n4/ye/l/en_US/llbKeTpY8ca.js",
      "details": {
        "id": "instagram",
        "message": "Dont embed instagram scripts, use your own embed"
      }
    },
    {
      "type": "instagram",
      "url": "https://static.cdninstagram.com/rsrc.php/v4/yF/r/JUQfRgDktxr.js",
      "details": {
        "id": "instagram",
        "message": "Dont embed instagram scripts, use your own embed"
      }
    },
    {
      "type": "instagram",
      "url": "https://static.cdninstagram.com/rsrc.php/v4ihVQ4/y4/l/en_US/tBdCjryrdB2.js",
      "details": {
        "id": "instagram",
        "message": "Dont embed instagram scripts, use your own embed"
      }
    },
    {
      "type": "instagram",
      "url": "https://static.cdninstagram.com/rsrc.php/v4/yO/r/FurF5tzLW7I.js",
      "details": {
        "id": "instagram",
        "message": "Dont embed instagram scripts, use your own embed"
      }
    },
    {
      "type": "instagram",
      "url": "https://static.cdninstagram.com/rsrc.php/v4/yF/r/EBVPsy6V8TR.js",
      "details": {
        "id": "instagram",
        "message": "Dont embed instagram scripts, use your own embed"
      }
    },
    {
      "type": "instagram",
      "url": "https://static.cdninstagram.com/rsrc.php/v4/yi/r/03YxQA42w6B.js",
      "details": {
        "id": "instagram",
        "message": "Dont embed instagram scripts, use your own embed"
      }
    },
    {
      "type": "instagram",
      "url": "https://scontent-lhr6-2.cdninstagram.com/v/t51.2885-15/483920772_18396597193096145_5734296250571458704_n.jpg?stp=dst-jpg_e15_tt6&_nc_ht=scontent-lhr6-2.cdninstagram.com&_nc_cat=105&_nc_oc=Q6cZ2QFYtQmnJCsi3DKtjp6qe9RwctAWAMcGnMPkGgobGwTo_oER6HoAkUy9ts-7TB-b7cY&_nc_ohc=8O0OJIIYfRwQ7kNvwFB_Ekn&_nc_gid=dlAwftw-0BsopJ-grV3xOQ&edm=APs17CUBAAAA&ccb=7-5&oh=00_AfQyBbMBy1YiVr5wdhQkjz9eQfe3uNtvfJpwNVNi_XW5ag&oe=686F98DE&_nc_sid=10d13b",
      "details": {
        "id": "instagram",
        "message": "Dont embed instagram scripts, use your own embed"
      }
    },
    {
      "type": "unknown",
      "url": "https://tarteaucitron.io/cache/lang/tarteaucitron.fr.min.js"
    },
    {
      "type": "unknown",
      "url": "https://tarteaucitron.io/cache/tarteaucitron.services.min.js"
    },
    {
      "type": "instagram",
      "url": "https://graph.instagram.com/logging_client_events",
      "details": {
        "id": "instagram",
        "message": "Dont embed instagram scripts, use your own embed"
      }
    },
    {
      "type": "instagram",
      "url": "https://graph.instagram.com/logging_client_events",
      "details": {
        "id": "instagram",
        "message": "Dont embed instagram scripts, use your own embed"
      }
    },
    {
      "type": "instagram",
      "url": "https://graph.instagram.com/logging_client_events",
      "details": {
        "id": "instagram",
        "message": "Dont embed instagram scripts, use your own embed"
      }
    },
    {
      "type": "instagram",
      "url": "https://graph.instagram.com/logging_client_events",
      "details": {
        "id": "instagram",
        "message": "Dont embed instagram scripts, use your own embed"
      }
    },
    {
      "type": "instagram",
      "url": "https://graph.instagram.com/logging_client_events",
      "details": {
        "id": "instagram",
        "message": "Dont embed instagram scripts, use your own embed"
      }
    },
    {
      "type": "unknown",
      "url": "https://tarteaucitron.io/log/?account=cb6c31eaf0d65c6f8768c5734dd1a8df6bfd7780&domain=nuitdesmusees.culture.gouv.fr&status=!mc_analytics%3Dfalse!siteimproveanalytics%3Dfalse!instagramembed%3Dfalse!twitterembed%3Dfalse&_time=1751765348937"
    }
  ],
  "cookies": [],
  "headers": {
    "accept-ranges": "bytes",
    "age": "4622",
    "cache-control": "public, s-maxage=86400, stale-while-revalidate=3600, stale-if-error=3600",
    "content-type": "text/html; charset=UTF-8",
    "date": "Sun, 06 Jul 2025 01:29:04 GMT",
    "referrer-policy": "no-referrer, strict-origin-when-cross-origin, no-referrer, strict-origin-when-cross-origin",
    "strict-transport-security": "max-age=31536000; includeSubDomains",
    "vary": "Origin,X-Editorial-Mode,X-Requested-With",
    "x-content-type-options": "nosniff",
    "x-cp-via": "C2-bfef82a6-5d16f56c",
    "x-forwarded-for": ";",
    "x-xss-protection": "1; mode=block; report=/nelmio/xss/report"
  },
  "endpoints": [
    {
      "hostname": "nuitdesmusees.culture.gouv.fr",
      "ip": "87.98.187.73",
      "geoip": {
        "continent": {
          "code": "EU",
          "geoname_id": 6255148,
          "names": {
            "de": "Europa",
            "en": "Europe",
            "es": "Europa",
            "fr": "Europe",
            "ja": "ヨーロッパ",
            "pt-BR": "Europa",
            "ru": "Европа",
            "zh-CN": "欧洲"
          }
        },
        "country": {
          "geoname_id": 3017382,
          "is_in_european_union": true,
          "iso_code": "FR",
          "names": {
            "de": "Frankreich",
            "en": "France",
            "es": "Francia",
            "fr": "France",
            "ja": "フランス共和国",
            "pt-BR": "França",
            "ru": "Франция",
            "zh-CN": "法国"
          }
        },
        "location": {
          "accuracy_radius": 500,
          "latitude": 48.8582,
          "longitude": 2.3387,
          "time_zone": "Europe/Paris"
        },
        "registered_country": {
          "geoname_id": 3017382,
          "is_in_european_union": true,
          "iso_code": "FR",
          "names": {
            "de": "Frankreich",
            "en": "France",
            "es": "Francia",
            "fr": "France",
            "ja": "フランス共和国",
            "pt-BR": "França",
            "ru": "Франция",
            "zh-CN": "法国"
          }
        }
      }
    },
    {
      "hostname": "infolettres.duministeredelaculture.fr",
      "ip": "54.38.64.29",
      "geoip": {
        "continent": {
          "code": "EU",
          "geoname_id": 6255148,
          "names": {
            "de": "Europa",
            "en": "Europe",
            "es": "Europa",
            "fr": "Europe",
            "ja": "ヨーロッパ",
            "pt-BR": "Europa",
            "ru": "Европа",
            "zh-CN": "欧洲"
          }
        },
        "country": {
          "geoname_id": 3017382,
          "is_in_european_union": true,
          "iso_code": "FR",
          "names": {
            "de": "Frankreich",
            "en": "France",
            "es": "Francia",
            "fr": "France",
            "ja": "フランス共和国",
            "pt-BR": "França",
            "ru": "Франция",
            "zh-CN": "法国"
          }
        },
        "location": {
          "accuracy_radius": 500,
          "latitude": 48.8582,
          "longitude": 2.3387,
          "time_zone": "Europe/Paris"
        },
        "registered_country": {
          "geoname_id": 3017382,
          "is_in_european_union": true,
          "iso_code": "FR",
          "names": {
            "de": "Frankreich",
            "en": "France",
            "es": "Francia",
            "fr": "France",
            "ja": "フランス共和国",
            "pt-BR": "França",
            "ru": "Франция",
            "zh-CN": "法国"
          }
        }
      }
    },
    {
      "hostname": "tarteaucitron.io",
      "ip": "51.68.111.231",
      "geoip": {
        "continent": {
          "code": "EU",
          "geoname_id": 6255148,
          "names": {
            "de": "Europa",
            "en": "Europe",
            "es": "Europa",
            "fr": "Europe",
            "ja": "ヨーロッパ",
            "pt-BR": "Europa",
            "ru": "Европа",
            "zh-CN": "欧洲"
          }
        },
        "country": {
          "geoname_id": 3017382,
          "is_in_european_union": true,
          "iso_code": "FR",
          "names": {
            "de": "Frankreich",
            "en": "France",
            "es": "Francia",
            "fr": "France",
            "ja": "フランス共和国",
            "pt-BR": "França",
            "ru": "Франция",
            "zh-CN": "法国"
          }
        },
        "location": {
          "accuracy_radius": 500,
          "latitude": 48.8582,
          "longitude": 2.3387,
          "time_zone": "Europe/Paris"
        },
        "registered_country": {
          "geoname_id": 3017382,
          "is_in_european_union": true,
          "iso_code": "FR",
          "names": {
            "de": "Frankreich",
            "en": "France",
            "es": "Francia",
            "fr": "France",
            "ja": "フランス共和国",
            "pt-BR": "França",
            "ru": "Франция",
            "zh-CN": "法国"
          }
        }
      }
    },
    {
      "hostname": "www.instagram.com",
      "ip": "157.240.254.174",
      "geoip": {
        "city": {
          "geoname_id": 4887398,
          "names": {
            "de": "Chicago",
            "en": "Chicago",
            "es": "Chicago",
            "fr": "Chicago",
            "ja": "シカゴ",
            "pt-BR": "Chicago",
            "ru": "Чикаго",
            "zh-CN": "芝加哥"
          }
        },
        "continent": {
          "code": "NA",
          "geoname_id": 6255149,
          "names": {
            "de": "Nordamerika",
            "en": "North America",
            "es": "Norteamérica",
            "fr": "Amérique du Nord",
            "ja": "北アメリカ",
            "pt-BR": "América do Norte",
            "ru": "Северная Америка",
            "zh-CN": "北美洲"
          }
        },
        "country": {
          "geoname_id": 6252001,
          "iso_code": "US",
          "names": {
            "de": "USA",
            "en": "United States",
            "es": "Estados Unidos",
            "fr": "États Unis",
            "ja": "アメリカ",
            "pt-BR": "EUA",
            "ru": "США",
            "zh-CN": "美国"
          }
        },
        "location": {
          "accuracy_radius": 20,
          "latitude": 41.8835,
          "longitude": -87.6305,
          "metro_code": 602,
          "time_zone": "America/Chicago"
        },
        "postal": {
          "code": "60602"
        },
        "registered_country": {
          "geoname_id": 6252001,
          "iso_code": "US",
          "names": {
            "de": "USA",
            "en": "United States",
            "es": "Estados Unidos",
            "fr": "États Unis",
            "ja": "アメリカ",
            "pt-BR": "EUA",
            "ru": "США",
            "zh-CN": "美国"
          }
        },
        "subdivisions": [
          {
            "geoname_id": 4896861,
            "iso_code": "IL",
            "names": {
              "de": "Illinois",
              "en": "Illinois",
              "es": "Illinois",
              "fr": "Illinois",
              "ja": "イリノイ州",
              "pt-BR": "Ilinóis",
              "ru": "Иллинойс",
              "zh-CN": "伊利诺伊州"
            }
          }
        ]
      }
    },
    {
      "hostname": "static.cdninstagram.com",
      "ip": "57.144.132.192",
      "geoip": {
        "city": {
          "geoname_id": 4205885,
          "names": {
            "de": "Lithia Springs",
            "en": "Lithia Springs",
            "es": "Lithia Springs",
            "fr": "Lithia Springs",
            "pt-BR": "Lithia Springs",
            "ru": "Лития-Спрингс"
          }
        },
        "continent": {
          "code": "NA",
          "geoname_id": 6255149,
          "names": {
            "de": "Nordamerika",
            "en": "North America",
            "es": "Norteamérica",
            "fr": "Amérique du Nord",
            "ja": "北アメリカ",
            "pt-BR": "América do Norte",
            "ru": "Северная Америка",
            "zh-CN": "北美洲"
          }
        },
        "country": {
          "geoname_id": 6252001,
          "iso_code": "US",
          "names": {
            "de": "USA",
            "en": "United States",
            "es": "Estados Unidos",
            "fr": "États Unis",
            "ja": "アメリカ",
            "pt-BR": "EUA",
            "ru": "США",
            "zh-CN": "美国"
          }
        },
        "location": {
          "accuracy_radius": 20,
          "latitude": 33.794,
          "longitude": -84.6605,
          "metro_code": 524,
          "time_zone": "America/New_York"
        },
        "postal": {
          "code": "30122"
        },
        "registered_country": {
          "geoname_id": 2963597,
          "is_in_european_union": true,
          "iso_code": "IE",
          "names": {
            "de": "Irland",
            "en": "Ireland",
            "es": "Irlanda",
            "fr": "Irlande",
            "ja": "アイルランド",
            "pt-BR": "Irlanda",
            "ru": "Ирландия",
            "zh-CN": "爱尔兰"
          }
        },
        "subdivisions": [
          {
            "geoname_id": 4197000,
            "iso_code": "GA",
            "names": {
              "de": "Georgia",
              "en": "Georgia",
              "es": "Georgia",
              "fr": "Géorgie",
              "ja": "ジョージア州",
              "pt-BR": "Geórgia",
              "ru": "Джорджия",
              "zh-CN": "乔治亚"
            }
          }
        ]
      }
    },
    {
      "hostname": "scontent-lhr6-2.cdninstagram.com",
      "ip": "163.70.151.63",
      "geoip": {
        "city": {
          "geoname_id": 2643743,
          "names": {
            "de": "London",
            "en": "London",
            "es": "Londres",
            "fr": "Londres",
            "ja": "ロンドン",
            "pt-BR": "Londres",
            "ru": "Лондон",
            "zh-CN": "伦敦"
          }
        },
        "continent": {
          "code": "EU",
          "geoname_id": 6255148,
          "names": {
            "de": "Europa",
            "en": "Europe",
            "es": "Europa",
            "fr": "Europe",
            "ja": "ヨーロッパ",
            "pt-BR": "Europa",
            "ru": "Европа",
            "zh-CN": "欧洲"
          }
        },
        "country": {
          "geoname_id": 2635167,
          "iso_code": "GB",
          "names": {
            "de": "UK",
            "en": "United Kingdom",
            "es": "Reino Unido",
            "fr": "Royaume-Uni",
            "ja": "英国",
            "pt-BR": "Reino Unido",
            "ru": "Британия",
            "zh-CN": "英国"
          }
        },
        "location": {
          "accuracy_radius": 20,
          "latitude": 51.5081,
          "longitude": -0.1278,
          "time_zone": "Europe/London"
        },
        "postal": {
          "code": "EC1N"
        },
        "registered_country": {
          "geoname_id": 2963597,
          "is_in_european_union": true,
          "iso_code": "IE",
          "names": {
            "de": "Irland",
            "en": "Ireland",
            "es": "Irlanda",
            "fr": "Irlande",
            "ja": "アイルランド",
            "pt-BR": "Irlanda",
            "ru": "Ирландия",
            "zh-CN": "爱尔兰"
          }
        },
        "subdivisions": [
          {
            "geoname_id": 6269131,
            "iso_code": "ENG",
            "names": {
              "de": "England",
              "en": "England",
              "es": "Inglaterra",
              "fr": "Angleterre",
              "ja": "イングランド",
              "pt-BR": "Inglaterra",
              "ru": "Англия",
              "zh-CN": "英格兰"
            }
          }
        ]
      }
    },
    {
      "hostname": "scontent-lhr8-2.cdninstagram.com",
      "ip": "157.240.214.63",
      "geoip": {
        "city": {
          "geoname_id": 2643743,
          "names": {
            "de": "London",
            "en": "London",
            "es": "Londres",
            "fr": "Londres",
            "ja": "ロンドン",
            "pt-BR": "Londres",
            "ru": "Лондон",
            "zh-CN": "伦敦"
          }
        },
        "continent": {
          "code": "EU",
          "geoname_id": 6255148,
          "names": {
            "de": "Europa",
            "en": "Europe",
            "es": "Europa",
            "fr": "Europe",
            "ja": "ヨーロッパ",
            "pt-BR": "Europa",
            "ru": "Европа",
            "zh-CN": "欧洲"
          }
        },
        "country": {
          "geoname_id": 2635167,
          "iso_code": "GB",
          "names": {
            "de": "UK",
            "en": "United Kingdom",
            "es": "Reino Unido",
            "fr": "Royaume-Uni",
            "ja": "英国",
            "pt-BR": "Reino Unido",
            "ru": "Британия",
            "zh-CN": "英国"
          }
        },
        "location": {
          "accuracy_radius": 20,
          "latitude": 51.5081,
          "longitude": -0.1278,
          "time_zone": "Europe/London"
        },
        "postal": {
          "code": "EC1N"
        },
        "registered_country": {
          "geoname_id": 6252001,
          "iso_code": "US",
          "names": {
            "de": "USA",
            "en": "United States",
            "es": "Estados Unidos",
            "fr": "États Unis",
            "ja": "アメリカ",
            "pt-BR": "EUA",
            "ru": "США",
            "zh-CN": "美国"
          }
        },
        "subdivisions": [
          {
            "geoname_id": 6269131,
            "iso_code": "ENG",
            "names": {
              "de": "England",
              "en": "England",
              "es": "Inglaterra",
              "fr": "Angleterre",
              "ja": "イングランド",
              "pt-BR": "Inglaterra",
              "ru": "Англия",
              "zh-CN": "英格兰"
            }
          }
        ]
      }
    },
    {
      "hostname": "scontent-lhr8-1.cdninstagram.com",
      "ip": "157.240.221.63",
      "geoip": {
        "city": {
          "geoname_id": 2643743,
          "names": {
            "de": "London",
            "en": "London",
            "es": "Londres",
            "fr": "Londres",
            "ja": "ロンドン",
            "pt-BR": "Londres",
            "ru": "Лондон",
            "zh-CN": "伦敦"
          }
        },
        "continent": {
          "code": "EU",
          "geoname_id": 6255148,
          "names": {
            "de": "Europa",
            "en": "Europe",
            "es": "Europa",
            "fr": "Europe",
            "ja": "ヨーロッパ",
            "pt-BR": "Europa",
            "ru": "Европа",
            "zh-CN": "欧洲"
          }
        },
        "country": {
          "geoname_id": 2635167,
          "iso_code": "GB",
          "names": {
            "de": "UK",
            "en": "United Kingdom",
            "es": "Reino Unido",
            "fr": "Royaume-Uni",
            "ja": "英国",
            "pt-BR": "Reino Unido",
            "ru": "Британия",
            "zh-CN": "英国"
          }
        },
        "location": {
          "accuracy_radius": 20,
          "latitude": 51.5081,
          "longitude": -0.1278,
          "time_zone": "Europe/London"
        },
        "postal": {
          "code": "EC1N"
        },
        "registered_country": {
          "geoname_id": 6252001,
          "iso_code": "US",
          "names": {
            "de": "USA",
            "en": "United States",
            "es": "Estados Unidos",
            "fr": "États Unis",
            "ja": "アメリカ",
            "pt-BR": "EUA",
            "ru": "США",
            "zh-CN": "美国"
          }
        },
        "subdivisions": [
          {
            "geoname_id": 6269131,
            "iso_code": "ENG",
            "names": {
              "de": "England",
              "en": "England",
              "es": "Inglaterra",
              "fr": "Angleterre",
              "ja": "イングランド",
              "pt-BR": "Inglaterra",
              "ru": "Англия",
              "zh-CN": "英格兰"
            }
          }
        ]
      }
    },
    {
      "hostname": "scontent-lhr6-1.cdninstagram.com",
      "ip": "163.70.147.63",
      "geoip": {
        "city": {
          "geoname_id": 2643743,
          "names": {
            "de": "London",
            "en": "London",
            "es": "Londres",
            "fr": "Londres",
            "ja": "ロンドン",
            "pt-BR": "Londres",
            "ru": "Лондон",
            "zh-CN": "伦敦"
          }
        },
        "continent": {
          "code": "EU",
          "geoname_id": 6255148,
          "names": {
            "de": "Europa",
            "en": "Europe",
            "es": "Europa",
            "fr": "Europe",
            "ja": "ヨーロッパ",
            "pt-BR": "Europa",
            "ru": "Европа",
            "zh-CN": "欧洲"
          }
        },
        "country": {
          "geoname_id": 2635167,
          "iso_code": "GB",
          "names": {
            "de": "UK",
            "en": "United Kingdom",
            "es": "Reino Unido",
            "fr": "Royaume-Uni",
            "ja": "英国",
            "pt-BR": "Reino Unido",
            "ru": "Британия",
            "zh-CN": "英国"
          }
        },
        "location": {
          "accuracy_radius": 20,
          "latitude": 51.5081,
          "longitude": -0.1278,
          "time_zone": "Europe/London"
        },
        "postal": {
          "code": "EC1N"
        },
        "registered_country": {
          "geoname_id": 2963597,
          "is_in_european_union": true,
          "iso_code": "IE",
          "names": {
            "de": "Irland",
            "en": "Ireland",
            "es": "Irlanda",
            "fr": "Irlande",
            "ja": "アイルランド",
            "pt-BR": "Irlanda",
            "ru": "Ирландия",
            "zh-CN": "爱尔兰"
          }
        },
        "subdivisions": [
          {
            "geoname_id": 6269131,
            "iso_code": "ENG",
            "names": {
              "de": "England",
              "en": "England",
              "es": "Inglaterra",
              "fr": "Angleterre",
              "ja": "イングランド",
              "pt-BR": "Inglaterra",
              "ru": "Англия",
              "zh-CN": "英格兰"
            }
          }
        ]
      }
    },
    {
      "hostname": "graph.instagram.com",
      "ip": "157.240.229.63",
      "geoip": {
        "city": {
          "geoname_id": 4744870,
          "names": {
            "de": "Ashburn",
            "en": "Ashburn",
            "es": "Ashburn",
            "fr": "Ashburn",
            "ja": "アッシュバーン",
            "pt-BR": "Ashburn",
            "ru": "Ашберн",
            "zh-CN": "阿什本"
          }
        },
        "continent": {
          "code": "NA",
          "geoname_id": 6255149,
          "names": {
            "de": "Nordamerika",
            "en": "North America",
            "es": "Norteamérica",
            "fr": "Amérique du Nord",
            "ja": "北アメリカ",
            "pt-BR": "América do Norte",
            "ru": "Северная Америка",
            "zh-CN": "北美洲"
          }
        },
        "country": {
          "geoname_id": 6252001,
          "iso_code": "US",
          "names": {
            "de": "USA",
            "en": "United States",
            "es": "Estados Unidos",
            "fr": "États Unis",
            "ja": "アメリカ",
            "pt-BR": "EUA",
            "ru": "США",
            "zh-CN": "美国"
          }
        },
        "location": {
          "accuracy_radius": 20,
          "latitude": 39.0469,
          "longitude": -77.4903,
          "metro_code": 511,
          "time_zone": "America/New_York"
        },
        "postal": {
          "code": "20149"
        },
        "registered_country": {
          "geoname_id": 6252001,
          "iso_code": "US",
          "names": {
            "de": "USA",
            "en": "United States",
            "es": "Estados Unidos",
            "fr": "États Unis",
            "ja": "アメリカ",
            "pt-BR": "EUA",
            "ru": "США",
            "zh-CN": "美国"
          }
        },
        "subdivisions": [
          {
            "geoname_id": 6254928,
            "iso_code": "VA",
            "names": {
              "de": "Virginia",
              "en": "Virginia",
              "es": "Virginia",
              "fr": "Virginie",
              "ja": "バージニア州",
              "pt-BR": "Virgínia",
              "ru": "Вирджиния",
              "zh-CN": "弗吉尼亚州"
            }
          }
        ]
      }
    }
  ]
}
